LICENSE
MANIFEST.in
README.md
setup.py
cube2sphere/__init__.py
cube2sphere/blender_init.py
cube2sphere/cube2sphere.py
cube2sphere/projector.blend
cube2sphere/version.py
cube2sphere.egg-info/PKG-INFO
cube2sphere.egg-info/SOURCES.txt
cube2sphere.egg-info/dependency_links.txt
cube2sphere.egg-info/entry_points.txt
cube2sphere.egg-info/top_level.txt