Metadata-Version: 2.1
Name: cube2sphere
Version: 0.2.1
Summary: Utility to map 6 cube (cubemap, skybox) faces into an equirectangular (cylindrical projection, skysphere) map
Home-page: http://github.com/Xyene/cube2sphere
Author: Tudor Brindus
Author-email: me@tbrindus.ca
License: UNKNOWN
Platform: UNKNOWN
Classifier: Development Status :: 3 - Alpha
Classifier: Environment :: Console
Classifier: Intended Audience :: Developers
Classifier: Programming Language :: Python :: 3
Classifier: Programming Language :: Python :: 3.5
Classifier: Programming Language :: Python :: 3.6
Classifier: Programming Language :: Python :: 3.7
Classifier: Programming Language :: Python :: 3.8
Classifier: License :: OSI Approved :: GNU Affero General Public License v3 or later (AGPLv3+)
Classifier: Operating System :: OS Independent
Classifier: Programming Language :: Python
Classifier: Topic :: Artistic Software
